MANIFEST.in
README.rst
pyproject.toml
setup.cfg
setup.py
tox.ini
docs/Makefile
docs/conf.py
docs/index.rst
docs/make.bat
docs/assets/logo.py
docs/assets/logo.svg
docs/tynt/api.rst
docs/tynt/customarchive.rst
docs/tynt/filters.rst
docs/tynt/gettingstarted.rst
docs/tynt/installation.rst
licenses/LICENSE.rst
licenses/README.rst
licenses/TEMPLATE_LICENSE.rst
tynt/__init__.py
tynt/core.py
tynt/download.py
tynt/version.py
tynt.egg-info/PKG-INFO
tynt.egg-info/SOURCES.txt
tynt.egg-info/dependency_links.txt
tynt.egg-info/not-zip-safe
tynt.egg-info/requires.txt
tynt.egg-info/top_level.txt
tynt/data/README.rst
tynt/data/fft.fits.zip
tynt/tests/__init__.py
tynt/tests/test_core.py