Metadata-Version: 2.1
Name: tynt
Version: 0.1.2
Summary: Astronomical filter bandpasses in Python
Home-page: https://github.com/bmorris3/tynt
Author: Brett M. Morris
Author-email: morrisbrettm@gmail.com
License: BSD 3-Clause
Requires-Python: >=3.10
License-File: licenses/LICENSE.rst
Requires-Dist: numpy
Requires-Dist: astropy
Provides-Extra: all
Requires-Dist: lxml; extra == "all"
Provides-Extra: test
Requires-Dist: pytest; extra == "test"
Requires-Dist: pytest-doctestplus; extra == "test"
Requires-Dist: pytest-cov; extra == "test"
Requires-Dist: pytest-astropy; extra == "test"
Provides-Extra: docs
Requires-Dist: sphinx; extra == "docs"
Requires-Dist: sphinx-automodapi; extra == "docs"
Requires-Dist: sphinx-astropy; extra == "docs"
Requires-Dist: matplotlib; extra == "docs"
Requires-Dist: pydata-sphinx-theme==0.8.1; extra == "docs"
Requires-Dist: sphinx-book-theme==0.3.3; extra == "docs"
Requires-Dist: numpydoc; extra == "docs"
